shetar/__init__.py
shetar/_version.py
shetar/bases.py
shetar/coordinates.py
shetar/expansions.py
shetar/rotations.py
shetar/translations.py
shetar-0.2.2.dist-info/LICENSE
shetar-0.2.2.dist-info/METADATA
shetar-0.2.2.dist-info/WHEEL
shetar-0.2.2.dist-info/top_level.txt
shetar-0.2.2.dist-info/RECORD
