Metadata-Version: 2.1
Name: shetar
Version: 0.2.2
Summary: Python implementations of fast multipole methods for the Helmholtz equation
Home-page: https://github.com/AppliedAcousticsChalmers/Spherical-Helmholtz-Translation-and-Rotation
Author: Carl Andersson
Author-email: carl.andersson@chalmers.se
License: MIT
Platform: UNKNOWN
Requires-Python: >=3.6
License-File: LICENSE
Requires-Dist: numpy
Requires-Dist: scipy
